genericpy/__init__.py
genericpy/generic.py
genericpy/generic.pyi
genericpy-0.0.1b3.dist-info/LICENSE
genericpy-0.0.1b3.dist-info/METADATA
genericpy-0.0.1b3.dist-info/WHEEL
genericpy-0.0.1b3.dist-info/top_level.txt
genericpy-0.0.1b3.dist-info/RECORD
