Metadata-Version: 2.1
Name: genericpy
Version: 0.0.1b3
Summary: This module helps introduce the real generics into class and functions.
Author-email: Caewinix <Caewinix@yeah.net>
Project-URL: Homepage, https://github.com/Caewinix/genericpy
Project-URL: Bug Tracker, https://github.com/Caewinix/genericpy/issues
Classifier: Programming Language :: Python :: 3
Classifier: License :: OSI Approved :: MIT License
Classifier: Operating System :: OS Independent
Requires-Python: >=3.7
License-File: LICENSE
Requires-Dist: pyreflex
